turtlekit/__init__.py
turtlekit/setup.py
turtlekit/turtlesuite.py
turtlekit-0.49.1.data/scripts/__init__.py
turtlekit-0.49.1.data/scripts/turtlesuite.py
turtlekit-0.49.1.dist-info/LICENSE
turtlekit-0.49.1.dist-info/METADATA
turtlekit-0.49.1.dist-info/WHEEL
turtlekit-0.49.1.dist-info/top_level.txt
turtlekit-0.49.1.dist-info/RECORD
